shortcuts/__init__.py
shortcuts/date.py
shortcuts/default.py
simple_shortcuts-0.1.0.dist-info/licenses/LICENSE
simple_shortcuts-0.1.0.dist-info/METADATA
simple_shortcuts-0.1.0.dist-info/WHEEL
simple_shortcuts-0.1.0.dist-info/top_level.txt
simple_shortcuts-0.1.0.dist-info/RECORD
