Metadata-Version: 2.4
Name: simple-shortcuts
Version: 0.1.0
Summary: A collection of handy python abstractions with simple and intuitive API's
Author-email: Ari Fishman <arifishman39@gmail.com>
License-Expression: Apache-2.0
Project-URL: Homepage, https://github.com/alfish1/simple-shortcuts
Project-URL: Repository, https://github.com/alfish1/simple-shortcuts
Requires-Python: >=3.9
License-File: LICENSE
Dynamic: license-file
